{
    "644316": "法广 | 被张伯礼院士“文革式”批判“价值观扭曲”  方方要求道歉",
    "644322": "自由亚洲 | 山东诗人鲁扬被控涉“颠覆国家政权”遭刑拘",
    "644355": "褚朝新说事｜小区门口的小店，最近已倒闭了4家",
    "644365": "【立此存照】胡锡进同学群聊天记录：你的国籍是中国还是美国？",
    "644385": "姚新勇：一个人建造的当代中国政治灾难史档案馆——序X先生的《“寻找”系列》",
    "644386": "德国之声 | 三十年来头一遭  澳门禁了天安门",
    "644394": "Photo: Untitled (Hangzhou), by xiquinhosilva",
    "644411": "【立此存照】人民日报英文版：他就是倒车之王！",
    "644418": "【图说天朝】“那我还有什么办法吗？”",
    "644422": "【图说天朝】禁止&#8221;明白&#8221;让人明白",
    "644475": "Photo: Cleaning the cityscape, by Bruno Abreu",
    "644482": "【中国哭墙】日出之美在于她脱胎于至暗的黑夜（5月16日）",
    "644491": "【网络民议】：小子，有海东这样的人盯着黑暗你才有机会享受更多光明",
    "644520": "单身者舞会｜方方战争：“递刀论”的旧答案和新问题",
    "644522": "林泉森｜方方日记接力之49: 我愿随喜这思想启蒙的传灯",
    "644528": "二湘的十一维空间｜杨胜慰：百日祭文亮，天使在人间",
    "644531": "纽约时间｜外交政策：大脱钩，美中关系进行时",
    "644541": "雪夜闭门读晋书 | 为什么必须盯住那场浩劫不放？",
    "644545": "南风窗 | 新冠痊愈者：“总觉得自己做错了什么事”",
    "644552": "丁东小群 | 点点滴滴崔卫平",
    "644555": "林三土 | 后六四时代的自由主义国际秩序",
    "644557": "【众人推】第一次发中文推不太懂事，说了点批评阿中哥的事，竟然，我妈没死",
    "644560": "坚果兄弟 |   举报一个公众号直到封号要多少钱，以”上海文学“为例",
    "644571": "莹莹观察 |  突发！张展寻衅滋事了",
    "644582": "【中国哭墙】如果你还活着，会不会被骂给抗疫抹黑，给外国递刀子？（5月17-18日）",
    "644588": "Matters | 出柜之后：被处分的同性恋教师",
    "644595": "它的票圈 | 在517发声的意义",
    "644602": "王犀知 | 2020，美国亡于中文自媒体",
    "644625": "ABC中文 |《纽约时报》资深驻华记者储百亮被迫离开中国",
    "644652": "【网络民议】请把这老小子调外交部  真是奇才啊",
    "644656": "为你写一个故事｜中文世界信息污染 真的到了不得不改变的时候",
    "644689": "书先生和路夫人｜我用AI分析了60篇方方日记，结果出人意料",
    "644704": "【中国哭墙】每个人都睁着眼睛，却看不清这世界（5月19日）",
    "644715": "Matters | 翻译失真所炮制的美国鄙夷：对比同一本书的台湾，大陆以及美国片段",
    "644723": "赵士林：士林夜话 | ‪格斗狂人的意义何在？",
    "644726": "德国之声 | 武汉50万人曾感染?新闻迅速“被消失”",
    "644776": "【对比新闻】扎克伯格：要学习习近平的著作 VS 中国的管理模式相当危险",
    "644783": "公民实验室｜微信监控诠释",
    "644796": "【立此存照】陕西汉滨一男子非法进行国际联网被查处",
    "644799": "丁咚｜澳大利亚为何敢于执意“单挑”中国？",
    "644802": "【CDTV】阿布鬧鬧：新疆街访后 来告诉你一些再教育集中营的真相",
    "644809": " 圣谛｜马师傅挨揍后的深刻探索：武术是怎么变成国术的",
    "644819": "大象公会｜教育的城乡差距，能在成人之后弥补吗？",
    "644829": "自由亚洲 |  官撑莲花清瘟片股价一度暴涨　高管暗割韭菜套现数亿股民焦头烂额",
    "644842": "【中国哭墙】再坚硬的心都会在这里软化（5月20日）",
    "644846": "美国之音 |  中国网络观察：“罗刹也在？”",
    "644849": "Photo: The Fish Sauce Chef &#8211; Xiapu, China, by Alex Berger",
    "644856": "沉思的托克维尔 | 都市中的中产青年：小粉红构成与动机分析",
    "644873": "BBC |  特朗普称世卫“中国傀儡” 公开信细数世卫抗疫14宗“罪”",
    "644884": "老凤财经 | 瑞幸是一面大旗，现在他倒了",
    "644910": "【朋友圈】这是一个多么恐怖的地方啊",
    "644917": "澎湃新闻｜外交部、国防部、国台办同日发表声明",
    "644928": "【网络民议】“我们也想与世界各国人民增进感情呀”",
    "644930": "【时代的一粒沙】计六一六： 被嫌弃的金大姐",
    "644935": "【网络民议】中国外交部强烈抗议，网民呵呵一笑而过，耳朵都免疫了",
    "644938": "【中国哭墙】抹去眼泪，只留下腮红浓重的谄媚笑脸…（5月21日）",
    "644944": "卖杏花 | 后悔救了敲锣女？真没必要",
    "644948": "许章润：世界文明大洋上的中国孤舟——全球体系背景下新冠疫情的政治观与文明论",
    "644964": "西雅图雷尼尔 | &#8220;五个一&#8221;政策将继续持续：海外留学生回国难",
    "644974": "i看见 | 我就是药神",
    "644977": "法广 | 只许州官“发Tweet”　不许百姓“翻墙” 港媒指防火墙争议",
    "644986": "【网络民议】两会召开北京“天有异象” 网友调侃“恶政隐”",
    "644999": "冇心音乐 |南京先锋书店因发布“我爱南京”盲盒，公众号被永丰。",
    "645015": "立场新闻 | 人大将审议“香港国安法制”决定草案  据报授权常委会立法  纳入《基本法》附件三直接在港实施",
    "645022": "【中国哭墙】他们踩着你的骨灰，从一个胜利走向另一个胜利（5月22日）",
    "645030": "奶白色星球 | 关于李志 热河 先锋书店和我爱南京的故事。",
    "645056": "德国之声 | 防疫为由断三十载烛光 港澳同被禁悼六四",
    "645059": "【网络民议】这是赵安法，不是国安法",
    "645061": "Matters | 端木皑：《港版国安法》：请国际手足出手相助！",
    "645068": "香港国安法：英美政界强烈谴责，寻求制裁中共官员",
    "645071": "附件三：“八九民运是在有国家安全法的地方发生的”",
    "645083": "【图说天朝】宇宙最重物质排行",
    "645097": "USDollar | 留学生回不了国，是因为“被美国扣为人质”了？",
    "645114": "【新闻连连看】“战疫新人”520很忙 又要云婚礼又要开罚单",
    "645125": "【对比新闻】2020年国务院政府工作报告两岸关系部分删去“和平”",
    "645127": "Photo: Victoria Harbour, by 57Andrew",
    "645132": "鱼眼观察 | 伊利犯了众怒",
    "645136": "Photo: Central Hong Kong, by 57Andrew",
    "645139": "【中国哭墙】李医生，请你保佑香港（5月23日）",
    "645147": "电影岛赏 | 电影学院的“后浪”们正在失去创作自由",
    "645157": "纽约华人资讯网 | 回不了的国：那些困在海外的中国人",
    "645169": "鱼眼观察｜伊利犯了众怒",
    "645173": "德国之声｜专访黄之锋：无惧国安法 跟习近平斗长命",
    "645176": "水浒商学院｜没有利好！两会第二天，资本市场雪崩",
    "645182": "凤凰WEEKLY｜城市底层劳动者的悲鸣：收入暴跌、随时失业，留不下的城市、回不去的故乡",
    "645188": "【麻辣总局】大雨后 主流媒体和自媒体的区别",
    "645193": "【异闻观止】“健康码”国家标准正式发布 未来或有更广泛应用",
    "645201": "Matters |  LunaLee：我家 ‧ 我城 ‧ 以後",
    "645204": "花开富贵老娘发飙 | 史上第一次，中国民航网被骂到关了评论！",
    "645215": "新世纪｜白宫发布《美国对中华人民共和国的战略方针》全文",
    "645220": "【图说天朝】没有任何文件符合你的搜寻：一国两制",
    "645226": "太平洋时区 | 至道学宫，栽了",
    "645228": "【图说天朝】全网江山一片红 总有一款适合你",
    "645243": "德国之声 | 泛民批港成&#8221;一国一制&#8221; 林郑月娥全力配合北京",
    "645248": "【中国哭墙】宇宙大元帅没和你打招呼就拿着20亿刀做梦去了（5月24-25日）",
    "645254": "光传媒 | 前政协委员王瑞琴致全国人大代表和政协委员的一封公开信",
    "645261": "美国之音 | 香港数以万计市民游击式游行 反对北京引入港版中国国安法",
    "645267": "冰川思享号 | 至道学宫这么坏的公号，为何在中国能赚那么多钱？",
    "645276": "酷玩实验室 | 国产芯片制造有多烂？十年饮冰，热血难凉",
    "645302": "【旧闻重温】中国商报｜财政部披露2019年预算 88%的钱花在哪了？"
}
