{
    "690921": "人间三角｜没人选择放开，是放开选择的我们",
    "690931": "每日一语 2022.12.15",
    "690933": "【CDT报告汇】无国界记者：中国仍然是关押记者最多的国家（外三篇）",
    "690934": "【404文库】“在‘全剧终’的时刻，我们不是退场的演员。我们都是历史的亲历者”（外二篇）",
    "690937": "韩青说书｜像流星一样划过：抗疫三年，民间江湖式自组织公益的兴起",
    "690941": "法度Law｜湖南娄底一学校因防疫不力被通报：班主任被“立案调查”",
    "690948": "王左中右｜四个字总结现在的抗阳生活",
    "690969": "【麻辣总局】槽逻辑｜漫画｜你精心准备，不如领导临场发挥……",
    "690971": "海涛评论｜无效药，总能供不应求",
    "690976": "海边的西塞罗｜解毒《三体》：人类就是不应该感谢罗辑",
    "690978": "每日一语 2022.12.16",
    "690981": "风声｜人们诟病的不是解封，而是解封之前该准备得更好",
    "690984": "【404帖子】知乎 ｜张峰答问：如何看待现在国家放开疫情管控？",
    "690989": "yaya的房间｜关于北京某医院现状的访谈",
    "690990": "往事陈列馆｜我们为什么会缺退烧药？",
    "690992": "贰條｜吴专家赢麻了！",
    "690994": "歪脑｜90后留学生在苹果门口绝食了七天，他图什么？",
    "690996": "每日一语 2022.12.16",
    "690999": "押沙龙yashl｜“工业党”们召唤黑暗森林，黑暗森林就会出现",
    "691001": "黄四娘家花满枝｜今天刷屏的两个突破人类道德底线",
    "691010": "【CDT周报】第100期：经过为期三年的全民牺牲，终于从阳性清零变成了阴性清零",
    "691011": "单读｜核酸基地里的医生：我们都是免费的耗材",
    "691012": "小鸟文学｜防疫工具退役了，没有人怀念它",
    "691013": "澎湃新闻｜退烧药为啥缺货？布洛芬巨头发话了",
    "691014": "每日一语 2022.12.18",
    "691017": "老萧杂说｜打疫苗绑定养老金，坏透顶的胁迫治理思维",
    "691020": "新京报｜新十条后，北京十日记",
    "691024": "读宋史的赵大胖｜我愿称他为“原地调头王”",
    "691027": "【网络民议】阳过后的生活用品不用更换，那之前破门消杀怎么说？",
    "691042": "NGOCN｜被捕者：那些青年",
    "691044": "【立此存照】后清零时代，北京健康宝重装上阵",
    "691047": "经济观察报｜最高法院原法官：因传播奥密克戎而被处罚的人，建议司法机关予以纠错",
    "691049": "【年终专题】被删除被屏蔽的，都是历史的亲历者……2022年度404文章",
    "691050": "每日一语 2022.12.19",
    "691059": "【CDTV】长沙中南大学湘雅附二医院医学专硕学生游行抗议要求返乡，学校领导组织线上讨论却以设备出错为由直接下线结束会议",
    "691062": "【CDTV】安徽合肥社区工作人员将健康包放在居民门口摆拍后拿走，官方回应是“送错了”，网友：“谢谢，还花时间糊弄人民”",
    "691063": "【年终专题】润、摆烂、非必要不XX……2022年度网络流行语",
    "691079": "【404文库】赛柏蓝｜买不到的布洛芬背后：禁令下，厂家一度不敢备货，现在临期药也被抢光",
    "691082": "【网络民议】美国的退烧药“也”缺货了",
    "691089": "人间三角｜我讨厌说什么杨过杨康",
    "691091": "澎湃新闻｜上海医院门急诊不再需要核酸，聚焦为核酸奔波的人们",
    "691094": "每日人物｜为什么我们买不到退烧药？",
    "691096": "六神磊磊读金庸｜这几年疫情下来的一点点体会",
    "691098": "贰條｜没有选择，都是借口。",
    "691100": "【404文库】“当我们放开的时候，居然什么都没有……什么都没有……没有……”（外二篇）",
    "691107": "每日一语 2022.12.21",
    "691109": "【网络民议】都要2023年了，共青团中央还在推荐放血疗法？",
    "691113": "格十三｜上网课不治疗新冠",
    "691115": "毛大庆｜从ICU到火葬场：疫情的扩散和正在经受考验的“城市韧性”",
    "691129": "【中国哭墙】李医生 时至今日 才懂那时您的无奈和绝望（12月18-24日，2022年）",
    "691133": "【年终专题】“不要领袖要选票，不做奴才做公民”&#8230;&#8230;2022年度名场面",
    "691154": "【年终专题】从“我的职责”到“我们的职责”……2022年度敏感词",
    "691155": "【CDTV】中国“动态清零”政策调整后，各地出现医院患者爆满等医疗挤兑情况",
    "691190": "【CDTV】各地疫情爆发，退烧药、感冒药一药难求，网民：“泱泱大国，百八十米一个大药房，我连一颗布洛芬都买不到”",
    "691200": "【年终专题】星火不灭：2022年华文媒体新生账号",
    "691201": "越秀山边｜对话李公明：请问国家医疗应急司，你们履行职责了吗？",
    "691204": "城市的地得｜我老家熬过了“疫情”",
    "691205": "新京报｜终至尾声，这家方舱医院送走最后一位患者",
    "691210": "【404文库】一钵行者｜有些“擅自接诊”发热病人的医生，现在还在坐牢",
    "691213": "维舟｜为什么有必要警惕饶毅们",
    "691216": "左拾遗｜南昌女子公开露面回应：看到警方通报，我觉得很可笑",
    "691229": "【年终专题】魔幻抗疫攻防战：2022年度“每日一语”",
    "691232": "【真理部】疫情防控报道提示和有关要求(2022年12月24日)",
    "691236": "上海法治报｜王锡锌：健康码彻底退出势在必行",
    "691238": "中国新闻周刊｜缺药、缺人、靠输液治疗，农村如何应对疫情冲击？",
    "691240": "每日一语 2022.12.24",
    "691248": "【CDT报告汇】中国疫情引发西方媒体关注，专家担心新一波疫情席卷全球（外二篇）",
    "691264": "【CDT周报】第101期：以前不让买退烧药，现在买不到退烧药",
    "691265": "槽边往事｜几个疑惑",
    "691267": "【404文库】连清川｜关于这个冬天，我有无数无解的问题",
    "691274": "基本常识｜停止发布疫情数据后，我们拿什么来直面现实？",
    "691280": "每日一语 2022.12.25",
    "691282": "一个生物狗的科普小园｜从99%是轻症无症状到医院重症很多是怎么回事？",
    "691284": "八点健闻｜大流行冲击乡镇农村：药库空，老人多，有乡镇做核酸自救",
    "691287": "维舟｜三年来观点一直没变的人，才被骂得最惨",
    "691290": "通向远方的道路｜人类不能白白遭受这场灾难",
    "691298": "每日一语 2022.12.26",
    "691305": "维舟｜神化张文宏的，其实是他的反对者们",
    "691307": "城市的地得｜生命的自主权：2022年告诉我的事",
    "691310": "【404文库】万小刀｜医院发喜报庆祝病人破200万，有何不妥？",
    "691316": "一小时爸爸｜昨天说自己5天感染2次新冠不同毒株的“病毒学博士”，当晚就“挂了”",
    "691318": "汉语言文学学习｜三年疫情创造或涉及的246个名词",
    "691325": "宅大医｜从辉瑞新冠药Paxlovid看高端医疗的阶层流动",
    "691327": "棉签小新｜殡仪馆现状",
    "691329": "虎嗅APP｜健康码不承担精准防疫功能后，个人信息怎么办？",
    "691331": "海边的西塞罗｜让我们对“清零派”，别像他们曾对我们那般不宽容",
    "691336": "【404文库】东瓯富商｜徐州丰县游记",
    "691350": "【翻车现场】人民日报用“12句话记住2022”，对于苦难却只字不提",
    "691356": "知识分子｜多地ICU告急，大白肺再现，奥密克戎的重症风险被低估了吗？",
    "691358": "时代周报｜我，核酸检测员，从月薪10万降至3万",
    "691361": "每日一语 2022.12.27",
    "691364": "棉签小新｜殡仪馆现状",
    "691365": "【404文库】“这样的群体免疫，还是群体免疫吗？这是群体受疫吧”（外二篇）",
    "691369": "【年终专题】“因为受够了夜晚就变成火炬，你举起了真正的自己”……2022年度人物：四通桥勇士彭立发与白纸抗议者",
    "691379": "左拾遗｜社科重大项目“伟大抗疫精神及其弘扬机制研究”，评论翻车…",
    "691381": "华夏泓康｜这些事情，恐怕是要“烂尾”了",
    "691383": "真实故事计划｜抢不到药的县城，偏方当道",
    "691400": "声道｜核酸检测员月入10万，这才是放开的原因",
    "691404": "和毛利午餐｜奥密克戎肆虐后的魔都，到处都是病友情",
    "691407": "每日一语 2022.12.28"
}
