{
    "682452": "【404文库】哥轮布碎碎报｜连清川：我们到底走出了什么？",
    "682455": "【图说天朝】只有在中国我才活得像一个病毒",
    "682476": "【立此存照】网信中国｜习近平与《格萨尔》",
    "682477": "陈亚亚｜谁是保卫社区的人？",
    "682479": "【404帖子】知乎提问：上海解封后的第1天，你是怎么度过的？有哪些不得不说的故事？",
    "682481": "每日一语 2022.6.1",
    "682485": "城市的地得｜“我最后哭了”：人如何不变成机器",
    "682490": "【404文库】【CDTV】《我们是最后一代》",
    "682498": "【真理部】6月3日至5日禁止用户修改头像、昵称、个人简介等",
    "682501": "【404文库】世界之敌的敌人｜原来上海从来没有封过城",
    "682504": "【404文库】基本常识｜假装地震没有发生",
    "682507": "天安门母亲｜六四惨案33周年祭",
    "682510": "每日一语 2022.6.2",
    "682512": "燕京书评｜伍子胥和屈原这两个楚人，端午节你愿意纪念谁？",
    "682524": "【重温】贫乏电影｜我身在历史何处",
    "682526": "世相研究所｜对，我要替这套“色情教材”洗白",
    "682527": "【CDT报道】六四33周年：德国驻华大使馆微博发布烛光图片被删除；“It&#8217;s my duty”",
    "682534": "【中国哭墙】李医生，好多人已经不知道今天的意义了（5月30-6月4日，2022年）",
    "682543": "【立此存照】澎湃新闻｜广西全州：检查发现新华字典及儿童读物存低俗化内容与配图，责令下架",
    "682551": "新公民计划｜六一特供 | 中国流动人口子女现状事实和数据2022",
    "682552": "【404文库】【CDTV】行为艺术/歌曲《阴性的翅膀》",
    "682558": "常识流通处｜“志愿者”与“大白”：被疫情毁坏的两个名词",
    "682560": "【404档案馆】第117期：六四屠杀后，并未结束的学运（上）",
    "682561": "【404档案馆】第118期：邹幸彤：守住六四烛光，守住我们良知的底线和仅余的自由",
    "682569": "每日一语 2022.6.3",
    "682598": "【敏感词库】It’s my duty、麦丢替",
    "682603": "英国驻华使馆｜彼得卢屠杀为什么会被英国铭记？",
    "682610": "NGOCN｜Sharon：一顶帐篷",
    "682616": "【CDT报告汇】中国人如何看待民主？美国谴责中国迫害宗教，以及中国大陆五月新增34名“良心犯”",
    "682621": "木蹊说｜郑州大学生打120求救，救护车2小时才到，而这家公司却火速中标核酸检测屋",
    "682623": "基本常识｜出事故的动车上座率仅23%，既是万幸也值得担心",
    "682626": "【CDTV】不会扫场所码的“离线”老人",
    "682633": "【404文库】小曹哥讲故事｜丰县派出所所长被评为全国优秀？还记得铁链女吗？",
    "682636": "歪脑｜生于六四后的人如何讨论六四： 这是不是我们记得六四的最后一代？",
    "682639": "每日一语 2022.6.4",
    "682643": "【404文库】一头驴的夜航船｜希望你好了伤疤，但别忘了痛",
    "682650": "旧闻评论｜要留下一个怎样的上海记忆？",
    "682652": "海边的西塞罗｜若我还在文明社会生活，就别要求我有荒野求生的能力",
    "682653": "【CDT周报】第72期：不要去喝庆功的酒，不要放下没报的仇",
    "682659": "【CDTV】用舞蹈无声地纪念六四",
    "682661": "每日一语 2022.6.5",
    "682663": "利维坦｜权力会损伤大脑吗？",
    "682665": "【立此存照】李佳琦悖论：你必须了解所有政治禁区才能不触碰政治禁区",
    "682692": "【网络民议】女人能上神舟不能上龙舟，真是片神奇的土地",
    "682707": "KnowYourself ｜ 上海解封为什么没有想象中开心？",
    "682708": "电影山海经｜上影节官宣今年停办，观众表示理解，但……",
    "682710": "真实故事计划｜留学生下沉到县城",
    "682712": "【404文库】贫乏电影｜我身在历史何处",
    "682714": "【404文库】数旗智酷｜健康码：数字巫术与色彩政治",
    "682721": "每日一语 2022.6.6",
    "682723": "先生制造｜欢迎来到中国A镇：保持距离，仰望高塔 | 新世界",
    "682726": "基本常识｜女性不能上龙舟的历史原因，比你想的更复杂",
    "682731": "【CDT网语】2022年5月：“我们是最后一代”",
    "682732": "格十三｜上海复工后，最先挤爆的是离婚登记",
    "682735": "【404视频】【CDTV】喇叭广播，竖中指，上海长乐路市民的抗争",
    "682739": "看理想｜解封后，我们都像“惊弓之鸟”",
    "682751": "【404文库】核酸常态化：在百姓排队与实验室造假中前行",
    "682755": "女权之声｜女性方舱生存战：解封后，我的“战斗”仍未结束",
    "682760": "【网络民议】朝阳区陆续安装大数据门禁管理系统  网友：这不是防疫，是奴役",
    "682762": "【异闻观止】人民网｜遇到“行走的50万”怎么办？指南收好！",
    "682764": "跟俞菱逛马路｜上海小店开门有多难！我们已疲惫不堪！",
    "682769": "微观系列｜荒唐事！昂贵的核酸亭才用一星期，多地纷纷弃用",
    "682772": "维舟的方舟｜上海不相信眼泪",
    "682774": "经济观察报｜河南核酸亭调查",
    "682777": "思维补丁｜原来“国企书记夫人”维权，也要躺在地上撒泼打滚",
    "682781": "听风言事｜被全州下架的《新华字典》，有着很多不为人知的秘密",
    "682783": "每日一语 2022.6.7",
    "682786": "权益墙李驯荒｜关注艺术家坚果兄弟失联：他曾帮助深圳城中村儿童、北京雾霾、LGBTQ+群体、冤案受害者、陕西小壕兔乡水污染受害者&#8230;",
    "682788": "【网络民议】骨子里是个强盗，也就只有强盗的想法",
    "682789": "人物｜一个大四女生，对「只招男生」说不",
    "682798": "【重温】流伞｜新疆集中营是个全球性问题",
    "682806": "【404视频】【CDTV】意外打脸全面脱贫？网民因拍摄大凉山婚宴遭喝茶",
    "682815": "【CDTV】安徽大叔质疑高考作文题目：你们拿北京的卷子来，摆饬我们安徽的孩子吗？",
    "682827": "特急大炮 ｜想当体制内男友，先学会“厅局风”穿搭",
    "682830": "史料搬运工｜不讲逻辑，强行深刻",
    "682832": "飞总聊IT｜震惊了美国人！字节跳动在美国输出中国式996",
    "682836": "还是不举手就发言｜中国企业家，开启“被动全球化”的征程",
    "682837": "每日一语 2022.6.8",
    "682841": "【麻辣总局】“坦克和我的佳琦，一刻也不能分离”",
    "682842": "维舟的方舟｜上海不相信眼泪",
    "682843": "无冕财经｜李佳琦“消失”6天，他们慌了",
    "682844": "王维洛｜六四”屠城、三峡工程与讲真实的历史",
    "682845": "好青年茶话会｜“人不可能远离政治远离公共话题”",
    "682866": "【404档案馆】第121期：“坦克雪糕”与“麦丢替”：审查制度下不灭的六四符号",
    "682868": "每日一语 2022.6.9",
    "682891": "【404文库】澎湃新闻｜疫情封锁时刻更需重温那些重要的常识",
    "682898": "为你写一个故事｜唐山打人事件，不要用来规训女性",
    "682900": "在人间｜瑞丽解封第九次：硬扛、冻结、重启",
    "682903": "学人Scholar｜徐贲谈微信十年：如何理解微信，它对我们的生活与内心产生了什么影响？",
    "682906": "三联生活周刊｜数百亿银行存款“消失”，几十万人的钱去哪了？",
    "682908": "基本常识｜越南核酸腐败大案给河南的三点温馨提醒",
    "682911": "每日一语 2022.6.10",
    "682915": "【中国哭墙】我们该怎么信任这个国家呢？（6月5-12日，2022年）",
    "682916": "【404文库】海鸥如是说｜从丰县到唐山——什么是系统性的性别暴力",
    "682920": "新默存｜台湾学生的随笔，为何能秒杀高考满分作文？",
    "682922": "【网络民议】深夜出门撸串？不好意思，X国给不了你这种安全感",
    "682934": "【404文库】雁记｜Po lice打了我，还说要传@@唤我",
    "682946": "【404文库】笨妈育儿育己｜“别搞性别对立！” 这话你去对着男人说啊！—唐山男子打人事件简评",
    "682956": "刀在这｜男性可以为女权主义做到的几件事（中特版",
    "682962": "做書｜大多数女性，远比你想象中更愤怒"
}
